UART/controleRecep.vhd
library IEEE;
use IEEE.STD_LOGIC_1164.ALL;

entity controleRecep is
    port (
        clk : in std_logic;
        reset : in std_logic;
        read : in std_logic;
        tmpclk : in std_logic;
        tmprxd : in std_logic;
        Ferr : out std_logic;
        OErr : out std_logic;
        DRdy : out std_logic;
        data : out std_logic_vector (7 downto 0)
    );
end controleRecep;

architecture behavorial of controleRecep is

    type t_etat is (debut, reception,reception_bis, verification_bit_p, verification_fin, fin);
    signal etat : t_etat;

begin

    process (clk,reset)

        variable data_aux : std_logic_vector (7 downto 0);
        variable bit_courant : natural;
        variable bit_p : std_logic;
        variable IndicateurOerr : std_logic;

    begin

        if (reset = '0') then
            IndicateurOerr := '0';
            Ferr <= '0';
            OErr <= '0';
            DRdy <= '0';
            data_aux := (others => '0');
            bit_courant := 7;
            bit_p := '0';
            data <= (others => '0');
            etat <= debut;

        elsif (rising_edge(clk)) then

            case etat is

                when debut =>

                    IndicateurOerr := '0';
                    Ferr <= '0';
                    OErr <= '0';
                    DRdy <= '0';

                    if (tmpclk = '1') then

                        data_aux := (others => '0');
                        bit_p := '0';
                        bit_courant := 7;
                        data <= (others => '0');
                        etat <= reception;

                    end if;
                
                when reception =>

                    if (tmpclk = '1') then

                        data_aux(bit_courant) := tmprxd;
                        bit_p := bit_p xor data_aux(bit_courant);
                        bit_courant := bit_courant - 1;
                        etat <= reception_bis;
                    
                    end if;

                when reception_bis =>

                    if (tmpclk = '1') then

                        data_aux(bit_courant) := tmprxd;
                        bit_p := bit_p xor data_aux(bit_courant);

                        if (bit_courant = 0) then

                            etat <= verification_bit_p;
                        
                        else

                            bit_courant := bit_courant - 1;
                        
                        end if;

                    end if;

                when verification_bit_p =>

                    if (tmpclk = '1') then

                        if (tmprxd /= bit_p) then

                            Ferr <= '1';
                            etat <= debut;
                        else
                            etat <= verification_fin;

                        end if;

                        

                    end if;

                when verification_fin =>

                    if (tmpclk = '1') then

                        if (tmprxd = '0') then

                            Ferr <= '1';
                            DRdy <= '0';
                            etat <= debut;

                        else
                            DRdy <= '1';
                            etat <= fin;
                        end if;
                    
                    end if;

                when fin =>

                    DRdy <= '0';

                    if (read = '0' and IndicateurOerr = '0') then
                        OErr <= '1';
                        IndicateurOerr := '1';
                    elsif (read = '0' and IndicateurOerr = '1') then
                        OErr <= '0';
                        etat <= debut;
                    else
                        etat <= debut;
                        data <= data_aux;
                    end if;

                end case;
            
            end if;

        end process;

end behavorial;

UART/compteur16.vhd
library IEEE;
use IEEE.STD_LOGIC_1164.ALL;

entity compteur16 is
    port (
        enable : in std_logic;
        reset  : in std_logic;
        rxd    : in std_logic;
        tmpclk : out std_logic;
        tmprxd : out std_logic
    );
end compteur16;

architecture structural of compteur16 is

    type t_etat is (debut, compter8, compter16, fin);
    signal etat : t_etat;

begin

    process (enable, reset)
        variable compt_iter : natural;
        variable compt_bit  : natural;

    begin

        if (reset = '0') then

            compt_bit := 0;
            compt_iter := 0;
            etat <= debut;
            tmpclk <= '0';
            tmprxd <= '1';

        elsif (rising_edge(enable)) then

            case etat is

                when debut =>

                    if (rxd = '0') then

                        compt_iter := 0;
                        compt_bit := 0;
                        tmpclk <= '0';
                        tmprxd <= '1';
                        etat <= compter8;
                    
                    end if;

                when compter8 =>

                    if (compt_iter = 7) then

                        tmpclk <= '1';
                        tmprxd <= rxd;
                        compt_bit := compt_bit + 1;
                        compt_iter := 0;
                        etat <= compter16;

                    else

                        compt_iter := compt_iter + 1;
                        tmpclk <= '0';
                    
                    end if;

                when compter16 =>

                    if (compt_iter = 15) then

                        if (compt_bit = 11) then

                            tmpclk <= '0';
                            etat <= fin;

                        else

                            compt_bit := compt_bit + 1;
                            compt_iter := 0;
                            tmpclk <= '1';
                            tmprxd <= rxd;
                            etat <= compter16;
									 
						end if;

                    else

                        compt_iter := compt_iter + 1;
                        tmpclk <= '0';
                    
                    end if;
                
                when fin =>

                    tmpclk <= '0';
                    tmprxd <= rxd;
                    etat <= debut;
                
                end case;

            end if;
    
    end process;

end structural;

UART/RxUnit.vhd
library IEEE;
use IEEE.std_logic_1164.all;

entity RxUnit is
  port (
    clk, reset       : in  std_logic;
    enable           : in  std_logic;
    read             : in  std_logic;
    rxd              : in  std_logic;
    data             : out std_logic_vector(7 downto 0);
    Ferr, OErr, DRdy : out std_logic);
end RxUnit;

architecture RxUnit_arch of RxUnit is

	component compteur16 is
		port (
			enable : in std_logic;
			reset  : in std_logic;
			rxd	   : in std_logic;
			tmpclk : out std_logic;
			tmprxd : out std_logic
		);
	end component;

	component controleRecep is
		port (
			clk 	: in std_logic;
			reset : in std_logic;
			tmpclk: in std_logic;
			tmprxd: in std_logic;
			read  : in std_logic;
			Ferr  : out std_logic;
			OErr  : out std_logic;
			DRdy  : out std_logic;
			data  : out std_logic_vector(7 downto 0)
		);
	end component;

	signal tmpclk_bis : std_logic;
	signal tmprxd_bis : std_logic;

begin
	
	Inst_compteur16 : compteur16 PORT MAP (
		enable => enable,
		reset => reset,
		rxd => rxd,
		tmpclk => tmpclk_bis,
		tmprxd => tmprxd_bis
	);

	Inst_controleRecep : controleRecep PORT MAP (
		clk => clk,
		reset => reset,
		read => read,
		tmpclk => tmpclk_bis,
		tmprxd => tmprxd_bis,
		Ferr => Ferr,
		OErr => OErr,
		DRdy => DRdy,
		data => data
	);
	
end RxUnit_arch;

UART/test_RxUnit_double_emission.vhd
LIBRARY ieee;
USE ieee.std_logic_1164.ALL;
 
-- Uncomment the following library declaration if using
-- arithmetic functions with Signed or Unsigned values
--USE ieee.numeric_std.ALL;
 
ENTITY test_RxUnit_double_emission IS
END test_RxUnit_double_emission;
 
ARCHITECTURE behavior OF test_RxUnit_double_emission IS 
 
    -- Component Declaration for the Unit Under Test (UUT)
 
    COMPONENT RxUnit
    PORT(
         clk : IN  std_logic;
         reset : IN  std_logic;
         enable : IN  std_logic;
         read : IN  std_logic;
         rxd : IN  std_logic;
         data : OUT  std_logic_vector(7 downto 0);
         FErr : OUT  std_logic;
         OErr : OUT  std_logic;
         DRdy : OUT  std_logic
        );
    END COMPONENT;
    

   --Inputs
   signal clk : std_logic := '0';
   signal reset : std_logic := '0';
   signal enable : std_logic := '0';
   signal rd : std_logic := '0';
   signal rxd : std_logic := '0';

 	--Outputs
   signal data : std_logic_vector(7 downto 0);
   signal FErr : std_logic;
   signal OErr : std_logic;
   signal DRdy : std_logic;

   -- Clock period definitions
   constant clk_period : time := 10 ns;
 
BEGIN
 
	-- Instantiate the Unit Under Test (UUT)
   uut: RxUnit PORT MAP (
          clk => clk,
          reset => reset,
          enable => enable,
          read => rd,
          rxd => rxd,
          data => data,
          FErr => FErr,
          OErr => OErr,
          DRdy => DRdy
        );

   -- Clock process definitions 
   clk_process :process
   begin
		clk <= '0';
		enable <= '0';
		wait for clk_period/2;
		clk <= '1';
      enable <= '1';
		wait for clk_period/2;
		
   end process;
 

   -- Stimulus process
   stim_proc: process
   begin		

      -- Test transmission normal --

		reset <= '0';
		rxd <= '1';

      -- hold reset state for 100 ns.
      wait for 100 ns;	
		reset <= '1';
		
		wait for clk_period*8;
		rxd <= '0'; -- Bit de start
		wait for clk_period*16;
		rxd <= '0'; -- Données 0101 0101
		wait for clk_period*16;
		rxd <= '1';
		wait for clk_period*16;
		rxd <= '0';
		wait for clk_period*16;
		rxd <= '1';
		wait for clk_period*16;
		rxd <= '0';
		wait for clk_period*16;
		rxd <= '1';
		wait for clk_period*16;
		rxd <= '0';
		wait for clk_period*16;
		rxd <= '1';
		wait for clk_period*16;
		rxd <= '0'; -- Bit de Parite
		wait for clk_period*16;
		rxd <= '1'; -- Bit de Stop
		
		wait until DRdy = '1';
      rd <= '1';
		wait until DRdy = '0';

		wait for clk_period*2;
		rd <= '0';
		
		wait for 500 ns;
      -- Test transmission bit de parité erroné --
     	reset <= '0';
		rxd <= '1';
      
      -- hold reset state for 100 ns.
      wait for 100 ns;	
		reset <= '1';
				
		wait for clk_period*8;
		rxd <= '0'; -- Bit de start
		wait for clk_period*16;
		rxd <= '1'; -- Données 1010 1010
		wait for clk_period*16;
		rxd <= '0';
		wait for clk_period*16;
		rxd <= '1';
		wait for clk_period*16;
		rxd <= '0';
		wait for clk_period*16;
		rxd <= '1';
		wait for clk_period*16;
		rxd <= '0';
		wait for clk_period*16;
		rxd <= '1';
		wait for clk_period*16;
		rxd <= '0';
		wait for clk_period*16;
		rxd <= '0'; -- Bit de Parite
		wait for clk_period*16;
		rxd <= '1';	-- Bit de Stop

        wait until DRdy = '1';
        rd <= '1';
          wait until DRdy = '0';
  
          wait for clk_period*2;
          rd <= '0';


      wait;
   end process;

END;

UART/output/output_double_emission.vcd
$date
   Tue Jan 17 17:46:40 2023
$end
$version
  P.20131013
$end
$timescale
  1ps
$end
$scope module test_rxunit_double_emission $end
$var wire 1 I clk $end
$var wire 1 J reset $end
$var wire 1 C enable $end
$var wire 1 K rd $end
$var wire 1 E rxd $end
$var wire 1 X data [7] $end
$var wire 1 W data [6] $end
$var wire 1 V data [5] $end
$var wire 1 U data [4] $end
$var wire 1 T data [3] $end
$var wire 1 S data [2] $end
$var wire 1 R data [1] $end
$var wire 1 Q data [0] $end
$var wire 1 N ferr $end
$var wire 1 O oerr $end
$var wire 1 P drdy $end
$scope module uut $end
$var wire 1 I clk $end
$var wire 1 J reset $end
$var wire 1 C enable $end
$var wire 1 K read $end
$var wire 1 E rxd $end
$var wire 1 X data [7] $end
$var wire 1 W data [6] $end
$var wire 1 V data [5] $end
$var wire 1 U data [4] $end
$var wire 1 T data [3] $end
$var wire 1 S data [2] $end
$var wire 1 R data [1] $end
$var wire 1 Q data [0] $end
$var wire 1 N ferr $end
$var wire 1 O oerr $end
$var wire 1 P drdy $end
$var wire 1 L tmpclk_bis $end
$var wire 1 M tmprxd_bis $end
$scope module Inst_compteur16 $end
$var wire 1 C enable $end
$var wire 1 J reset $end
$var wire 1 E rxd $end
$var wire 1 L tmpclk $end
$var wire 1 M tmprxd $end
$upscope $end
$scope module Inst_controleRecep $end
$var wire 1 I clk $end
$var wire 1 J reset $end
$var wire 1 K read $end
$var wire 1 L tmpclk $end
$var wire 1 M tmprxd $end
$var wire 1 N ferr $end
$var wire 1 O oerr $end
$var wire 1 P drdy $end
$var wire 1 X data [7] $end
$var wire 1 W data [6] $end
$var wire 1 V data [5] $end
$var wire 1 U data [4] $end
$var wire 1 T data [3] $end
$var wire 1 S data [2] $end
$var wire 1 R data [1] $end
$var wire 1 Q data [0] $end
$upscope $end
$upscope $end
$upscope $end
$enddefinitions $end
#0
$dumpvars
0I
0J
0C
0K
1E
0X
0W
0V
0U
0T
0S
0R
0Q
0N
0O
0P
0L
1M
$end
#5000
1I
1C
#10000
0I
0C
#15000
1I
1C
#20000
0I
0C
#25000
1I
1C
#30000
0I
0C
#35000
1I
1C
#40000
0I
0C
#45000
1I
1C
#50000
0I
0C
#55000
1I
1C
#60000
0I
0C
#65000
1I
1C
#70000
0I
0C
#75000
1I
1C
#80000
0I
0C
#85000
1I
1C
#90000
0I
0C
#95000
1I
1C
#100000
0I
1J
0C
#105000
1I
1C
#110000
0I
0C
#115000
1I
1C
#120000
0I
0C
#125000
1I
1C
#130000
0I
0C
#135000
1I
1C
#140000
0I
0C
#145000
1I
1C
#150000
0I
0C
#155000
1I
1C
#160000
0I
0C
#165000
1I
1C
#170000
0I
0C
#175000
1I
1C
#180000
0I
0C
0E
#185000
1I
1C
#190000
0I
0C
#195000
1I
1C
#200000
0I
0C
#205000
1I
1C
#210000
0I
0C
#215000
1I
1C
#220000
0I
0C
#225000
1I
1C
#230000
0I
0C
#235000
1I
1C
#240000
0I
0C
#245000
1I
1C
#250000
0I
0C
#255000
1I
1C
#260000
0I
0C
#265000
1I
1C
1L
0M
#270000
0I
0C
#275000
1I
1C
0L
#280000
0I
0C
#285000
1I
1C
#290000
0I
0C
#295000
1I
1C
#300000
0I
0C
#305000
1I
1C
#310000
0I
0C
#315000
1I
1C
#320000
0I
0C
#325000
1I
1C
#330000
0I
0C
#335000
1I
1C
#340000
0I
0C
#345000
1I
1C
#350000
0I
0C
#355000
1I
1C
#360000
0I
0C
#365000
1I
1C
#370000
0I
0C
#375000
1I
1C
#380000
0I
0C
#385000
1I
1C
#390000
0I
0C
#395000
1I
1C
#400000
0I
0C
#405000
1I
1C
#410000
0I
0C
#415000
1I
1C
#420000
0I
0C
#425000
1I
1C
1L
#430000
0I
0C
#435000
1I
1C
0L
#440000
0I
0C
#445000
1I
1C
#450000
0I
0C
#455000
1I
1C
#460000
0I
0C
#465000
1I
1C
#470000
0I
0C
#475000
1I
1C
#480000
0I
0C
#485000
1I
1C
#490000
0I
0C
#495000
1I
1C
#500000
0I
0C
1E
#505000
1I
1C
#510000
0I
0C
#515000
1I
1C
#520000
0I
0C
#525000
1I
1C
#530000
0I
0C
#535000
1I
1C
#540000
0I
0C
#545000
1I
1C
#550000
0I
0C
#555000
1I
1C
#560000
0I
0C
#565000
1I
1C
#570000
0I
0C
#575000
1I
1C
#580000
0I
0C
#585000
1I
1C
1L
1M
#590000
0I
0C
#595000
1I
1C
0L
#600000
0I
0C
#605000
1I
1C
#610000
0I
0C
#615000
1I
1C
#620000
0I
0C
#625000
1I
1C
#630000
0I
0C
#635000
1I
1C
#640000
0I
0C
#645000
1I
1C
#650000
0I
0C
#655000
1I
1C
#660000
0I
0C
0E
#665000
1I
1C
#670000
0I
0C
#675000
1I
1C
#680000
0I
0C
#685000
1I
1C
#690000
0I
0C
#695000
1I
1C
#700000
0I
0C
#705000
1I
1C
#710000
0I
0C
#715000
1I
1C
#720000
0I
0C
#725000
1I
1C
#730000
0I
0C
#735000
1I
1C
#740000
0I
0C
#745000
1I
1C
1L
0M
#750000
0I
0C
#755000
1I
1C
0L
#760000
0I
0C
#765000
1I
1C
#770000
0I
0C
#775000
1I
1C
#780000
0I
0C
#785000
1I
1C
#790000
0I
0C
#795000
1I
1C
#800000
0I
0C
#805000
1I
1C
#810000
0I
0C
#815000
1I
1C
#820000
0I
0C
1E
#825000
1I
1C
#830000
0I
0C
#835000
1I
1C
#840000
0I
0C
#845000
1I
1C
#850000
0I
0C
#855000
1I
1C
#860000
0I
0C
#865000
1I
1C
#870000
0I
0C
#875000
1I
1C
#880000
0I
0C
#885000
1I
1C
#890000
0I
0C
#895000
1I
1C
#900000
0I
0C
#905000
1I
1C
1L
1M
#910000
0I
0C
#915000
1I
1C
0L
#920000
0I
0C
#925000
1I
1C
#930000
0I
0C
#935000
1I
1C
#940000
0I
0C
#945000
1I
1C
#950000
0I
0C
#955000
1I
1C
#960000
0I
0C
#965000
1I
1C
#970000
0I
0C
#975000
1I
1C
#980000
0I
0C
0E
#985000
1I
1C
#990000
0I
0C
#995000
1I
1C
#1000000
0I
0C
#1005000
1I
1C
#1010000
0I
0C
#1015000
1I
1C
#1020000
0I
0C
#1025000
1I
1C
#1030000
0I
0C
#1035000
1I
1C
#1040000
0I
0C
#1045000
1I
1C
#1050000
0I
0C
#1055000
1I
1C
#1060000
0I
0C
#1065000
1I
1C
1L
0M
#1070000
0I
0C
#1075000
1I
1C
0L
#1080000
0I
0C
#1085000
1I
1C
#1090000
0I
0C
#1095000
1I
1C
#1100000
0I
0C
#1105000
1I
1C
#1110000
0I
0C
#1115000
1I
1C
#1120000
0I
0C
#1125000
1I
1C
#1130000
0I
0C
#1135000
1I
1C
#1140000
0I
0C
1E
#1145000
1I
1C
#1150000
0I
0C
#1155000
1I
1C
#1160000
0I
0C
#1165000
1I
1C
#1170000
0I
0C
#1175000
1I
1C
#1180000
0I
0C
#1185000
1I
1C
#1190000
0I
0C
#1195000
1I
1C
#1200000
0I
0C
#1205000
1I
1C
#1210000
0I
0C
#1215000
1I
1C
#1220000
0I
0C
#1225000
1I
1C
1L
1M
#1230000
0I
0C
#1235000
1I
1C
0L
#1240000
0I
0C
#1245000
1I
1C
#1250000
0I
0C
#1255000
1I
1C
#1260000
0I
0C
#1265000
1I
1C
#1270000
0I
0C
#1275000
1I
1C
#1280000
0I
0C
#1285000
1I
1C
#1290000
0I
0C
#1295000
1I
1C
#1300000
0I
0C
0E
#1305000
1I
1C
#1310000
0I
0C
#1315000
1I
1C
#1320000
0I
0C
#1325000
1I
1C
#1330000
0I
0C
#1335000
1I
1C
#1340000
0I
0C
#1345000
1I
1C
#1350000
0I
0C
#1355000
1I
1C
#1360000
0I
0C
#1365000
1I
1C
#1370000
0I
0C
#1375000
1I
1C
#1380000
0I
0C
#1385000
1I
1C
1L
0M
#1390000
0I
0C
#1395000
1I
1C
0L
#1400000
0I
0C
#1405000
1I
1C
#1410000
0I
0C
#1415000
1I
1C
#1420000
0I
0C
#1425000
1I
1C
#1430000
0I
0C
#1435000
1I
1C
#1440000
0I
0C
#1445000
1I
1C
#1450000
0I
0C
#1455000
1I
1C
#1460000
0I
0C
1E
#1465000
1I
1C
#1470000
0I
0C
#1475000
1I
1C
#1480000
0I
0C
#1485000
1I
1C
#1490000
0I
0C
#1495000
1I
1C
#1500000
0I
0C
#1505000
1I
1C
#1510000
0I
0C
#1515000
1I
1C
#1520000
0I
0C
#1525000
1I
1C
#1530000
0I
0C
#1535000
1I
1C
#1540000
0I
0C
#1545000
1I
1C
1L
1M
#1550000
0I
0C
#1555000
1I
1C
0L
#1560000
0I
0C
#1565000
1I
1C
#1570000
0I
0C
#1575000
1I
1C
#1580000
0I
0C
#1585000
1I
1C
#1590000
0I
0C
#1595000
1I
1C
#1600000
0I
0C
#1605000
1I
1C
#1610000
0I
0C
#1615000
1I
1C
#1620000
0I
0C
0E
#1625000
1I
1C
#1630000
0I
0C
#1635000
1I
1C
#1640000
0I
0C
#1645000
1I
1C
#1650000
0I
0C
#1655000
1I
1C
#1660000
0I
0C
#1665000
1I
1C
#1670000
0I
0C
#1675000
1I
1C
#1680000
0I
0C
#1685000
1I
1C
#1690000
0I
0C
#1695000
1I
1C
#1700000
0I
0C
#1705000
1I
1C
1L
0M
#1710000
0I
0C
#1715000
1I
1C
0L
#1720000
0I
0C
#1725000
1I
1C
#1730000
0I
0C
#1735000
1I
1C
#1740000
0I
0C
#1745000
1I
1C
#1750000
0I
0C
#1755000
1I
1C
#1760000
0I
0C
#1765000
1I
1C
#1770000
0I
0C
#1775000
1I
1C
#1780000
0I
0C
1E
#1785000
1I
1C
#1790000
0I
0C
#1795000
1I
1C
#1800000
0I
0C
#1805000
1I
1C
#1810000
0I
0C
#1815000
1I
1C
#1820000
0I
0C
#1825000
1I
1C
#1830000
0I
0C
#1835000
1I
1C
#1840000
0I
0C
#1845000
1I
1C
#1850000
0I
0C
#1855000
1I
1C
#1860000
0I
0C
#1865000
1I
1C
1L
1M
#1870000
0I
0C
#1875000
1I
1C
1K
1P
0L
#1880000
0I
0C
#1885000
1I
1C
1W
1U
1S
1Q
0P
#1890000
0I
0C
#1895000
1I
1C
#1900000
0I
0C
#1905000
1I
1C
0K
#1910000
0I
0C
#1915000
1I
1C
#1920000
0I
0C
#1925000
1I
1C
#1930000
0I
0C
#1935000
1I
1C
#1940000
0I
0C
#1945000
1I
1C
#1950000
0I
0C
#1955000
1I
1C
#1960000
0I
0C
#1965000
1I
1C
#1970000
0I
0C
#1975000
1I
1C
#1980000
0I
0C
#1985000
1I
1C
#1990000
0I
0C
#1995000
1I
1C
#2000000
0I
0C
#2005000
1I
1C
#2010000
0I
0C
#2015000
1I
1C
#2020000
0I
0C
#2025000
1I
1C
#2030000
0I
0C
#2035000
1I
1C
#2040000
0I
0C
#2045000
1I
1C
#2050000
0I
0C
#2055000
1I
1C
#2060000
0I
0C
#2065000
1I
1C
#2070000
0I
0C
#2075000
1I
1C
#2080000
0I
0C
#2085000
1I
1C
#2090000
0I
0C
#2095000
1I
1C
#2100000
0I
0C
#2105000
1I
1C
#2110000
0I
0C
#2115000
1I
1C
#2120000
0I
0C
#2125000
1I
1C
#2130000
0I
0C
#2135000
1I
1C
#2140000
0I
0C
#2145000
1I
1C
#2150000
0I
0C
#2155000
1I
1C
#2160000
0I
0C
#2165000
1I
1C
#2170000
0I
0C
#2175000
1I
1C
#2180000
0I
0C
#2185000
1I
1C
#2190000
0I
0C
#2195000
1I
1C
#2200000
0I
0C
#2205000
1I
1C
#2210000
0I
0C
#2215000
1I
1C
#2220000
0I
0C
#2225000
1I
1C
#2230000
0I
0C
#2235000
1I
1C
#2240000
0I
0C
#2245000
1I
1C
#2250000
0I
0C
#2255000
1I
1C
#2260000
0I
0C
#2265000
1I
1C
#2270000
0I
0C
#2275000
1I
1C
#2280000
0I
0C
#2285000
1I
1C
#2290000
0I
0C
#2295000
1I
1C
#2300000
0I
0C
#2305000
1I
1C
#2310000
0I
0C
#2315000
1I
1C
#2320000
0I
0C
#2325000
1I
1C
#2330000
0I
0C
#2335000
1I
1C
#2340000
0I
0C
#2345000
1I
1C
#2350000
0I
0C
#2355000
1I
1C
#2360000
0I
0C
#2365000
1I
1C
#2370000
0I
0C
#2375000
1I
1C
#2380000
0I
0C
#2385000
1I
1C
#2390000
0I
0C
#2395000
1I
1C
#2400000
0I
0C
#2405000
1I
0J
1C
0W
0U
0S
0Q
#2410000
0I
0C
#2415000
1I
1C
#2420000
0I
0C
#2425000
1I
1C
#2430000
0I
0C
#2435000
1I
1C
#2440000
0I
0C
#2445000
1I
1C
#2450000
0I
0C
#2455000
1I
1C
#2460000
0I
0C
#2465000
1I
1C
#2470000
0I
0C
#2475000
1I
1C
#2480000
0I
0C
#2485000
1I
1C
#2490000
0I
0C
#2495000
1I
1C
#2500000
0I
0C
#2505000
1I
1J
1C
#2510000
0I
0C
#2515000
1I
1C
#2520000
0I
0C
#2525000
1I
1C
#2530000
0I
0C
#2535000
1I
1C
#2540000
0I
0C
#2545000
1I
1C
#2550000
0I
0C
#2555000
1I
1C
#2560000
0I
0C
#2565000
1I
1C
#2570000
0I
0C
#2575000
1I
1C
#2580000
0I
0C
#2585000
1I
1C
0E
#2590000
0I
0C
#2595000
1I
1C
#2600000
0I
0C
#2605000
1I
1C
#2610000
0I
0C
#2615000
1I
1C
#2620000
0I
0C
#2625000
1I
1C
#2630000
0I
0C
#2635000
1I
1C
#2640000
0I
0C
#2645000
1I
1C
#2650000
0I
0C
#2655000
1I
1C
#2660000
0I
0C
#2665000
1I
1C
1L
0M
#2670000
0I
0C
#2675000
1I
1C
0L
#2680000
0I
0C
#2685000
1I
1C
#2690000
0I
0C
#2695000
1I
1C
#2700000
0I
0C
#2705000
1I
1C
#2710000
0I
0C
#2715000
1I
1C
#2720000
0I
0C
#2725000
1I
1C
#2730000
0I
0C
#2735000
1I
1C
#2740000
0I
0C
#2745000
1I
1C
1E
#2750000
0I
0C
#2755000
1I
1C
#2760000
0I
0C
#2765000
1I
1C
#2770000
0I
0C
#2775000
1I
1C
#2780000
0I
0C
#2785000
1I
1C
#2790000
0I
0C
#2795000
1I
1C
#2800000
0I
0C
#2805000
1I
1C
#2810000
0I
0C
#2815000
1I
1C
#2820000
0I
0C
#2825000
1I
1C
1L
1M
#2830000
0I
0C
#2835000
1I
1C
0L
#2840000
0I
0C
#2845000
1I
1C
#2850000
0I
0C
#2855000
1I
1C
#2860000
0I
0C
#2865000
1I
1C
#2870000
0I
0C
#2875000
1I
1C
#2880000
0I
0C
#2885000
1I
1C
#2890000
0I
0C
#2895000
1I
1C
#2900000
0I
0C
#2905000
1I
1C
0E
#2910000
0I
0C
#2915000
1I
1C
#2920000
0I
0C
#2925000
1I
1C
#2930000
0I
0C
#2935000
1I
1C
#2940000
0I
0C
#2945000
1I
1C
#2950000
0I
0C
#2955000
1I
1C
#2960000
0I
0C
#2965000
1I
1C
#2970000
0I
0C
#2975000
1I
1C
#2980000
0I
0C
#2985000
1I
1C
1L
0M
#2990000
0I
0C
#2995000
1I
1C
0L
#3000000
0I
0C
#3005000
1I
1C
#3010000
0I
0C
#3015000
1I
1C
#3020000
0I
0C
#3025000
1I
1C
#3030000
0I
0C
#3035000
1I
1C
#3040000
0I
0C
#3045000
1I
1C
#3050000
0I
0C
#3055000
1I
1C
#3060000
0I
0C
#3065000
1I
1C
1E
#3070000
0I
0C
#3075000
1I
1C
#3080000
0I
0C
#3085000
1I
1C
#3090000
0I
0C
#3095000
1I
1C
#3100000
0I
0C
#3105000
1I
1C
#3110000
0I
0C
#3115000
1I
1C
#3120000
0I
0C
#3125000
1I
1C
#3130000
0I
0C
#3135000
1I
1C
#3140000
0I
0C
#3145000
1I
1C
1L
1M
#3150000
0I
0C
#3155000
1I
1C
0L
#3160000
0I
0C
#3165000
1I
1C
#3170000
0I
0C
#3175000
1I
1C
#3180000
0I
0C
#3185000
1I
1C
#3190000
0I
0C
#3195000
1I
1C
#3200000
0I
0C
#3205000
1I
1C
#3210000
0I
0C
#3215000
1I
1C
#3220000
0I
0C
#3225000
1I
1C
0E
#3230000
0I
0C
#3235000
1I
1C
#3240000
0I
0C
#3245000
1I
1C
#3250000
0I
0C
#3255000
1I
1C
#3260000
0I
0C
#3265000
1I
1C
#3270000
0I
0C
#3275000
1I
1C
#3280000
0I
0C
#3285000
1I
1C
#3290000
0I
0C
#3295000
1I
1C
#3300000
0I
0C
#3305000
1I
1C
1L
0M
#3310000
0I
0C
#3315000
1I
1C
0L
#3320000
0I
0C
#3325000
1I
1C
#3330000
0I
0C
#3335000
1I
1C
#3340000
0I
0C
#3345000
1I
1C
#3350000
0I
0C
#3355000
1I
1C
#3360000
0I
0C
#3365000
1I
1C
#3370000
0I
0C
#3375000
1I
1C
#3380000
0I
0C
#3385000
1I
1C
1E
#3390000
0I
0C
#3395000
1I
1C
#3400000
0I
0C
#3405000
1I
1C
#3410000
0I
0C
#3415000
1I
1C
#3420000
0I
0C
#3425000
1I
1C
#3430000
0I
0C
#3435000
1I
1C
#3440000
0I
0C
#3445000
1I
1C
#3450000
0I
0C
#3455000
1I
1C
#3460000
0I
0C
#3465000
1I
1C
1L
1M
#3470000
0I
0C
#3475000
1I
1C
0L
#3480000
0I
0C
#3485000
1I
1C
#3490000
0I
0C
#3495000
1I
1C
#3500000
0I
0C
#3505000
1I
1C
#3510000
0I
0C
#3515000
1I
1C
#3520000
0I
0C
#3525000
1I
1C
#3530000
0I
0C
#3535000
1I
1C
#3540000
0I
0C
#3545000
1I
1C
0E
#3550000
0I
0C
#3555000
1I
1C
#3560000
0I
0C
#3565000
1I
1C
#3570000
0I
0C
#3575000
1I
1C
#3580000
0I
0C
#3585000
1I
1C
#3590000
0I
0C
#3595000
1I
1C
#3600000
0I
0C
#3605000
1I
1C
#3610000
0I
0C
#3615000
1I
1C
#3620000
0I
0C
#3625000
1I
1C
1L
0M
#3630000
0I
0C
#3635000
1I
1C
0L
#3640000
0I
0C
#3645000
1I
1C
#3650000
0I
0C
#3655000
1I
1C
#3660000
0I
0C
#3665000
1I
1C
#3670000
0I
0C
#3675000
1I
1C
#3680000
0I
0C
#3685000
1I
1C
#3690000
0I
0C
#3695000
1I
1C
#3700000
0I
0C
#3705000
1I
1C
1E
#3710000
0I
0C
#3715000
1I
1C
#3720000
0I
0C
#3725000
1I
1C
#3730000
0I
0C
#3735000
1I
1C
#3740000
0I
0C
#3745000
1I
1C
#3750000
0I
0C
#3755000
1I
1C
#3760000
0I
0C
#3765000
1I
1C
#3770000
0I
0C
#3775000
1I
1C
#3780000
0I
0C
#3785000
1I
1C
1L
1M
#3790000
0I
0C
#3795000
1I
1C
0L
#3800000
0I
0C
#3805000
1I
1C
#3810000
0I
0C
#3815000
1I
1C
#3820000
0I
0C
#3825000
1I
1C
#3830000
0I
0C
#3835000
1I
1C
#3840000
0I
0C
#3845000
1I
1C
#3850000
0I
0C
#3855000
1I
1C
#3860000
0I
0C
#3865000
1I
1C
0E
#3870000
0I
0C
#3875000
1I
1C
#3880000
0I
0C
#3885000
1I
1C
#3890000
0I
0C
#3895000
1I
1C
#3900000
0I
0C
#3905000
1I
1C
#3910000
0I
0C
#3915000
1I
1C
#3920000
0I
0C
#3925000
1I
1C
#3930000
0I
0C
#3935000
1I
1C
#3940000
0I
0C
#3945000
1I
1C
1L
0M
#3950000
0I
0C
#3955000
1I
1C
0L
#3960000
0I
0C
#3965000
1I
1C
#3970000
0I
0C
#3975000
1I
1C
#3980000
0I
0C
#3985000
1I
1C
#3990000
0I
0C
#3995000
1I
1C
#4000000
0I
0C
#4005000
1I
1C
#4010000
0I
0C
#4015000
1I
1C
#4020000
0I
0C
#4025000
1I
1C
#4030000
0I
0C
#4035000
1I
1C
#4040000
0I
0C
#4045000
1I
1C
#4050000
0I
0C
#4055000
1I
1C
#4060000
0I
0C
#4065000
1I
1C
#4070000
0I
0C
#4075000
1I
1C
#4080000
0I
0C
#4085000
1I
1C
#4090000
0I
0C
#4095000
1I
1C
#4100000
0I
0C
#4105000
1I
1C
1L
#4110000
0I
0C
#4115000
1I
1C
0L
#4120000
0I
0C
#4125000
1I
1C
#4130000
0I
0C
#4135000
1I
1C
#4140000
0I
0C
#4145000
1I
1C
#4150000
0I
0C
#4155000
1I
1C
#4160000
0I
0C
#4165000
1I
1C
#4170000
0I
0C
#4175000
1I
1C
#4180000
0I
0C
#4185000
1I
1C
1E
#4190000
0I
0C
#4195000
1I
1C
#4200000
0I
0C
#4205000
1I
1C
#4210000
0I
0C
#4215000
1I
1C
#4220000
0I
0C
#4225000
1I
1C
#4230000
0I
0C
#4235000
1I
1C
#4240000
0I
0C
#4245000
1I
1C
#4250000
0I
0C
#4255000
1I
1C
#4260000
0I
0C
#4265000
1I
1C
1L
1M
#4270000
0I
0C
#4275000
1I
1C
1K
1P
0L
#4280000
0I
0C
#4285000
1I
1C
1X
1V
1T
1R
0P
#4290000
0I
0C
#4295000
1I
1C
#4300000
0I
0C
#4305000
1I
1C
0K
#4310000
0I
0C
