UART/RxUnit.vhd
library IEEE;
use IEEE.std_logic_1164.all;

entity RxUnit is
  port (
    clk, reset       : in  std_logic;
    enable           : in  std_logic;
    read             : in  std_logic;
    rxd              : in  std_logic;
    data             : out std_logic_vector(7 downto 0);
    Ferr, OErr, DRdy : out std_logic);
end RxUnit;

architecture RxUnit_arch of RxUnit is

	 type t_etat_compt is (debut, compter8, compter16, fin);
    signal etat_compt : t_etat_compt;
    type t_etat_recep is (debut, reception, verification_bit_p, verification_stop, fin);
    signal etat_recep : t_etat_recep;
	
	signal tmpclk : std_logic;
	signal tmprxd : std_logic;

begin
    -- Process du compteur
	compteur : process (enable, reset)
	
    variable compt_iter : natural;
   variable compt_bit  : natural;

    begin
        if (reset = '0') then
            -- Reset
            compt_bit := 0;
            compt_iter := 0;
            etat_compt <= debut;
            tmpclk <= '0';
            tmprxd <= '1';

        elsif (rising_edge(enable)) then

            case etat_compt is

                when debut =>

                    if (rxd = '0') then
                        -- On attend le premier bit de start
                        compt_iter := 0;
                        compt_bit := 0;
                        tmpclk <= '0';
                        tmprxd <= '1';
                        etat_compt <= compter8;
                    end if;
                when compter8 =>
                -- On compte 8 pour arriver au milieu du bit de start
                    if (compt_iter = 7) then
                        -- On a compté 8 itérations, donc on est au milieu du bit de start
                        tmpclk <= '1';
                        tmprxd <= rxd;
                        compt_bit := compt_bit + 1;
                        compt_iter := 0;
                        etat_compt <= compter16;
                    else
                        -- On incrémente le compteur d'itération
                        compt_iter := compt_iter + 1;
                        tmpclk <= '0';
                    
                    end if;
                when compter16 =>
                -- On compte 16 pour arriver au milieu du deuxième bit de data
                    if (compt_iter = 15) then
                        -- On a compté 16 itérations, donc on est au milieu d'un bit
                        if (compt_bit = 11) then
                            -- Si on a compté 12 bits, on a fini
                            tmpclk <= '0';
                            etat_compt <= fin;
                        else
                            -- Sinon on continue
                            compt_bit := compt_bit + 1;
                            compt_iter := 0;
                            tmpclk <= '1';
                            tmprxd <= rxd;
                            etat_compt <= compter16; 
						end if;
                    else
                    -- On incrémente le compteur d'itération
                        compt_iter := compt_iter + 1;
                        tmpclk <= '0';
                    end if;
                when fin =>
                    -- On a fini, on attend le prochain bit de start
                    tmpclk <= '0';
                    tmprxd <= rxd;
                    etat_compt <= debut;      
                end case;

            end if;
    
    end process compteur;
	-- Process du controle de la reception
	controle_recep : process(clk,reset)
	
	variable data_aux : std_logic_vector (7 downto 0);
        variable bit_courant : natural;
        variable bit_p : std_logic;
        variable IndicateurOerr : std_logic;

    begin
        -- Réinitialisation
        if (reset = '0') then
            IndicateurOerr := '0';
            Ferr <= '0';
            OErr <= '0';
            DRdy <= '0';
            data_aux := (others => '0');
            bit_courant := 7;
            bit_p := '0';
            data <= (others => '0');
            etat_recep <= debut;

        elsif (rising_edge(clk)) then

            case etat_recep is

                when debut =>
                    -- Retour au début on remet les valeurs à 0
                    IndicateurOerr := '0';
                    Ferr <= '0';
                    OErr <= '0';
                    DRdy <= '0';
                    if (tmpclk = '1') then
                        data_aux := (others => '0'); -- Initialisation de la data temporaire
                        bit_p := '0';                -- Initialisation du bit de parité
                        bit_courant := 7;            -- Initialisation du compteur de bit
                        data <= (others => '0');     -- Initialisation de la data
                        etat_recep <= reception;     -- Passage dans l'état de reception
                    end if;
                when reception =>
                    if (tmpclk = '1') then
                        data_aux(bit_courant) := tmprxd;            -- Réception des bits un à un sur ka data temporaire
                        bit_p := bit_p xor data_aux(bit_courant);   -- Calcul progressif du bit de parité
                        if (bit_courant = 0) then
                            -- Tous les bits de donnée ont été reçus, on pass à l'état suivant
                            etat_recep <= verification_bit_p;
                        else
                            -- On décrément de le bit courant si la donnée n'a pas totalement été reçue
                            bit_courant := bit_courant - 1;
                        end if;
                    end if;
                when verification_bit_p =>
                    if (tmpclk = '1') then
                        if (tmprxd /= bit_p) then
                            -- Le bit de parité est erroné on lève une erreur et on retourne au début
                            Ferr <= '1';
                            etat_recep <= debut;
                        else
                            -- Pas d'erreur de bit de parité on passe dans l'état suivant
                            etat_recep <= verification_stop;
                        end if;
                    end if;
                when verification_stop =>
                    if (tmpclk = '1') then
                        if (tmprxd = '0') then
                            -- Le bit de stop est erroné on retourne au début et o lève une erreur de type Ferr
                            Ferr <= '1';
                            etat_recep <= debut;
                        else
                            -- On charge la data temporaire dans la data dans le cas contraire, on indique qu'une lecture est possible et
                            -- on passe dans l'état suivant
                            DRdy <= '1';
							data <= data_aux;
							etat_recep <= fin;
						end if;
                    end if;
					  when fin =>
						 if (read = '0' and IndicateurOerr = '0') then
                                -- Si la donnée n'a pas été lue, on lève une erreur de type OErr
								OErr <= '1';
								IndicateurOerr := '1';
						  end if;
                          -- Retour dans l'état initial
                          etat_recep <= debut;
                end case;
            
            end if;

        end process controle_recep;

end RxUnit_arch;

UART/test_RxUnit_read_absent.vhd
LIBRARY ieee;
USE ieee.std_logic_1164.ALL;
 
-- Uncomment the following library declaration if using
-- arithmetic functions with Signed or Unsigned values
--USE ieee.numeric_std.ALL;
 
ENTITY test_RxUnit_read_absent IS
END test_RxUnit_read_absent;
 
ARCHITECTURE behavior OF test_RxUnit_read_absent IS 
 
    -- Component Declaration for the Unit Under Test (UUT)
 
    COMPONENT RxUnit
    PORT(
         clk : IN  std_logic;
         reset : IN  std_logic;
         enable : IN  std_logic;
         read : IN  std_logic;
         rxd : IN  std_logic;
         data : OUT  std_logic_vector(7 downto 0);
         FErr : OUT  std_logic;
         OErr : OUT  std_logic;
         DRdy : OUT  std_logic
        );
    END COMPONENT;
    

   --Inputs
   signal clk : std_logic := '0';
   signal reset : std_logic := '0';
   signal enable : std_logic := '0';
   signal rd : std_logic := '0';
   signal rxd : std_logic := '0';

 	--Outputs
   signal data : std_logic_vector(7 downto 0);
   signal FErr : std_logic;
   signal OErr : std_logic;
   signal DRdy : std_logic;

   -- Clock period definitions
   constant clk_period : time := 10 ns;
 
BEGIN
 
	-- Instantiate the Unit Under Test (UUT)
   uut: RxUnit PORT MAP (
          clk => clk,
          reset => reset,
          enable => enable,
          read => rd,
          rxd => rxd,
          data => data,
          FErr => FErr,
          OErr => OErr,
          DRdy => DRdy
        );

   -- Clock process definitions 
   clk_process :process
   begin
		clk <= '0';
		enable <= '0';
		wait for clk_period/2;
		clk <= '1';
      enable <= '1';
		wait for clk_period/2;
		
   end process;
 

   -- Stimulus process
   stim_proc: process
   begin		
      -- Test transmission read absent --
     	reset <= '0';
		rxd <= '1';
      
      -- hold reset state for 100 ns.
      wait for 100 ns;	
		reset <= '1';
				
		wait for clk_period*8;
		rxd <= '0'; -- Bit de start
		wait for clk_period*16;
		rxd <= '0'; -- Données 0101 0101
		wait for clk_period*16;
		rxd <= '1';
		wait for clk_period*16;
		rxd <= '0';
		wait for clk_period*16;
		rxd <= '1';
		wait for clk_period*16;
		rxd <= '0';
		wait for clk_period*16;
		rxd <= '1';
		wait for clk_period*16;
		rxd <= '0';
		wait for clk_period*16;
		rxd <= '1';
		wait for clk_period*16;
		rxd <= '0'; -- Bit de Parite
		wait for clk_period*16;
		rxd <= '1'; -- Bit de Stop


      wait;
   end process;

END;

UART/output/output_read_absent.vcd
$date
   Fri Jan 20 13:06:44 2023
$end
$version
  P.20131013
$end
$timescale
  1ps
$end
$scope module test_rxunit_read_absent $end
$var wire 1 1 clk $end
$var wire 1 2 reset $end
$var wire 1 3 enable $end
$var wire 1 4 rd $end
$var wire 1 5 rxd $end
$var wire 1 = data [7] $end
$var wire 1 < data [6] $end
$var wire 1 ; data [5] $end
$var wire 1 : data [4] $end
$var wire 1 9 data [3] $end
$var wire 1 8 data [2] $end
$var wire 1 7 data [1] $end
$var wire 1 6 data [0] $end
$var wire 1 > ferr $end
$var wire 1 ? oerr $end
$var wire 1 @ drdy $end
$scope module uut $end
$var wire 1 1 clk $end
$var wire 1 2 reset $end
$var wire 1 3 enable $end
$var wire 1 4 read $end
$var wire 1 5 rxd $end
$var wire 1 = data [7] $end
$var wire 1 < data [6] $end
$var wire 1 ; data [5] $end
$var wire 1 : data [4] $end
$var wire 1 9 data [3] $end
$var wire 1 8 data [2] $end
$var wire 1 7 data [1] $end
$var wire 1 6 data [0] $end
$var wire 1 > ferr $end
$var wire 1 ? oerr $end
$var wire 1 @ drdy $end
$var wire 1 C tmpclk $end
$var wire 1 D tmprxd $end
$upscope $end
$upscope $end
$enddefinitions $end
#0
$dumpvars
02
03
04
15
0=
0<
0;
0:
09
08
07
06
0>
0?
0@
0C
1D
01
$end
#5000
13
11
#10000
03
01
#15000
13
11
#20000
03
01
#25000
13
11
#30000
03
01
#35000
13
11
#40000
03
01
#45000
13
11
#50000
03
01
#55000
13
11
#60000
03
01
#65000
13
11
#70000
03
01
#75000
13
11
#80000
03
01
#85000
13
11
#90000
03
01
#95000
13
11
#100000
12
03
01
#105000
13
11
#110000
03
01
#115000
13
11
#120000
03
01
#125000
13
11
#130000
03
01
#135000
13
11
#140000
03
01
#145000
13
11
#150000
03
01
#155000
13
11
#160000
03
01
#165000
13
11
#170000
03
01
#175000
13
11
#180000
03
05
01
#185000
13
11
#190000
03
01
#195000
13
11
#200000
03
01
#205000
13
11
#210000
03
01
#215000
13
11
#220000
03
01
#225000
13
11
#230000
03
01
#235000
13
11
#240000
03
01
#245000
13
11
#250000
03
01
#255000
13
11
#260000
03
01
#265000
13
1C
0D
11
#270000
03
01
#275000
13
0C
11
#280000
03
01
#285000
13
11
#290000
03
01
#295000
13
11
#300000
03
01
#305000
13
11
#310000
03
01
#315000
13
11
#320000
03
01
#325000
13
11
#330000
03
01
#335000
13
11
#340000
03
01
#345000
13
11
#350000
03
01
#355000
13
11
#360000
03
01
#365000
13
11
#370000
03
01
#375000
13
11
#380000
03
01
#385000
13
11
#390000
03
01
#395000
13
11
#400000
03
01
#405000
13
11
#410000
03
01
#415000
13
11
#420000
03
01
#425000
13
1C
11
#430000
03
01
#435000
13
0C
11
#440000
03
01
#445000
13
11
#450000
03
01
#455000
13
11
#460000
03
01
#465000
13
11
#470000
03
01
#475000
13
11
#480000
03
01
#485000
13
11
#490000
03
01
#495000
13
11
#500000
03
15
01
#505000
13
11
#510000
03
01
#515000
13
11
#520000
03
01
#525000
13
11
#530000
03
01
#535000
13
11
#540000
03
01
#545000
13
11
#550000
03
01
#555000
13
11
#560000
03
01
#565000
13
11
#570000
03
01
#575000
13
11
#580000
03
01
#585000
13
1C
1D
11
#590000
03
01
#595000
13
0C
11
#600000
03
01
#605000
13
11
#610000
03
01
#615000
13
11
#620000
03
01
#625000
13
11
#630000
03
01
#635000
13
11
#640000
03
01
#645000
13
11
#650000
03
01
#655000
13
11
#660000
03
05
01
#665000
13
11
#670000
03
01
#675000
13
11
#680000
03
01
#685000
13
11
#690000
03
01
#695000
13
11
#700000
03
01
#705000
13
11
#710000
03
01
#715000
13
11
#720000
03
01
#725000
13
11
#730000
03
01
#735000
13
11
#740000
03
01
#745000
13
1C
0D
11
#750000
03
01
#755000
13
0C
11
#760000
03
01
#765000
13
11
#770000
03
01
#775000
13
11
#780000
03
01
#785000
13
11
#790000
03
01
#795000
13
11
#800000
03
01
#805000
13
11
#810000
03
01
#815000
13
11
#820000
03
15
01
#825000
13
11
#830000
03
01
#835000
13
11
#840000
03
01
#845000
13
11
#850000
03
01
#855000
13
11
#860000
03
01
#865000
13
11
#870000
03
01
#875000
13
11
#880000
03
01
#885000
13
11
#890000
03
01
#895000
13
11
#900000
03
01
#905000
13
1C
1D
11
#910000
03
01
#915000
13
0C
11
#920000
03
01
#925000
13
11
#930000
03
01
#935000
13
11
#940000
03
01
#945000
13
11
#950000
03
01
#955000
13
11
#960000
03
01
#965000
13
11
#970000
03
01
#975000
13
11
#980000
03
05
01
#985000
13
11
#990000
03
01
#995000
13
11
#1000000
03
01
#1005000
13
11
#1010000
03
01
#1015000
13
11
#1020000
03
01
#1025000
13
11
#1030000
03
01
#1035000
13
11
#1040000
03
01
#1045000
13
11
#1050000
03
01
#1055000
13
11
#1060000
03
01
#1065000
13
1C
0D
11
#1070000
03
01
#1075000
13
0C
11
#1080000
03
01
#1085000
13
11
#1090000
03
01
#1095000
13
11
#1100000
03
01
#1105000
13
11
#1110000
03
01
#1115000
13
11
#1120000
03
01
#1125000
13
11
#1130000
03
01
#1135000
13
11
#1140000
03
15
01
#1145000
13
11
#1150000
03
01
#1155000
13
11
#1160000
03
01
#1165000
13
11
#1170000
03
01
#1175000
13
11
#1180000
03
01
#1185000
13
11
#1190000
03
01
#1195000
13
11
#1200000
03
01
#1205000
13
11
#1210000
03
01
#1215000
13
11
#1220000
03
01
#1225000
13
1C
1D
11
#1230000
03
01
#1235000
13
0C
11
#1240000
03
01
#1245000
13
11
#1250000
03
01
#1255000
13
11
#1260000
03
01
#1265000
13
11
#1270000
03
01
#1275000
13
11
#1280000
03
01
#1285000
13
11
#1290000
03
01
#1295000
13
11
#1300000
03
05
01
#1305000
13
11
#1310000
03
01
#1315000
13
11
#1320000
03
01
#1325000
13
11
#1330000
03
01
#1335000
13
11
#1340000
03
01
#1345000
13
11
#1350000
03
01
#1355000
13
11
#1360000
03
01
#1365000
13
11
#1370000
03
01
#1375000
13
11
#1380000
03
01
#1385000
13
1C
0D
11
#1390000
03
01
#1395000
13
0C
11
#1400000
03
01
#1405000
13
11
#1410000
03
01
#1415000
13
11
#1420000
03
01
#1425000
13
11
#1430000
03
01
#1435000
13
11
#1440000
03
01
#1445000
13
11
#1450000
03
01
#1455000
13
11
#1460000
03
15
01
#1465000
13
11
#1470000
03
01
#1475000
13
11
#1480000
03
01
#1485000
13
11
#1490000
03
01
#1495000
13
11
#1500000
03
01
#1505000
13
11
#1510000
03
01
#1515000
13
11
#1520000
03
01
#1525000
13
11
#1530000
03
01
#1535000
13
11
#1540000
03
01
#1545000
13
1C
1D
11
#1550000
03
01
#1555000
13
0C
11
#1560000
03
01
#1565000
13
11
#1570000
03
01
#1575000
13
11
#1580000
03
01
#1585000
13
11
#1590000
03
01
#1595000
13
11
#1600000
03
01
#1605000
13
11
#1610000
03
01
#1615000
13
11
#1620000
03
05
01
#1625000
13
11
#1630000
03
01
#1635000
13
11
#1640000
03
01
#1645000
13
11
#1650000
03
01
#1655000
13
11
#1660000
03
01
#1665000
13
11
#1670000
03
01
#1675000
13
11
#1680000
03
01
#1685000
13
11
#1690000
03
01
#1695000
13
11
#1700000
03
01
#1705000
13
1C
0D
11
#1710000
03
01
#1715000
13
0C
11
#1720000
03
01
#1725000
13
11
#1730000
03
01
#1735000
13
11
#1740000
03
01
#1745000
13
11
#1750000
03
01
#1755000
13
11
#1760000
03
01
#1765000
13
11
#1770000
03
01
#1775000
13
11
#1780000
03
15
01
#1785000
13
11
#1790000
03
01
#1795000
13
11
#1800000
03
01
#1805000
13
11
#1810000
03
01
#1815000
13
11
#1820000
03
01
#1825000
13
11
#1830000
03
01
#1835000
13
11
#1840000
03
01
#1845000
13
11
#1850000
03
01
#1855000
13
11
#1860000
03
01
#1865000
13
1C
1D
11
#1870000
03
01
#1875000
13
1<
1:
18
16
1@
0C
11
#1880000
03
01
#1885000
13
1?
0@
11
#1890000
03
01
#1895000
13
11
#1900000
03
01
#1905000
13
0?
11
#1910000
03
01
#1915000
13
11
#1920000
03
01
#1925000
13
11
#1930000
03
01
#1935000
13
11
#1940000
03
01
#1945000
13
11
#1950000
03
01
#1955000
13
11
#1960000
03
01
#1965000
13
11
#1970000
03
01
#1975000
13
11
#1980000
03
01
#1985000
13
11
#1990000
03
01
#1995000
13
11
#2000000
03
01
